{"cookies":[{"name":"YSC","value":"pcxoBlvo0Ao","domain":".youtube.com","path":"/","expires":-1,"size":14,"httpOnly":true,"secure":true,"session":true,"sameSite":"None"},{"name":"PREF","value":"tz=UTC","domain":".youtube.com","path":"/","expires":1691154761,"size":10,"httpOnly":false,"secure":true,"session":false},{"name":"CONSENT","value":"YES+yt.388297243.en+FX+348","domain":".youtube.com","path":"/","expires":2146723199.141422,"size":33,"httpOnly":false,"secure":true,"session":false,"sameSite":"None"},{"name":"VISITOR_INFO1_LIVE","value":"2Z2u3ugwcdM","domain":".youtube.com","path":"/","expires":1643634758.079164,"size":29,"httpOnly":true,"secure":true,"session":false,"sameSite":"None"},{"name":"CONSENT","value":"YES+yt.388297243.en+FX+198","domain":".google.com","path":"/","expires":2146723199.229814,"size":33,"httpOnly":false,"secure":true,"session":false,"sameSite":"None"},{"name":"NID","value":"220=sivnDkZG14Yx-tjZ4uPXIY81CiZQI5vdz-KR6vnHUUg3Gi0dowbnUswHM8vUBDuW_wZNKAH5yBOhWgdBEoX0AESptDANLSk86BktKhNabEo73xTyHOoWMMuwV34j3zG2DJmpre-wJXp5bVFkApy0qDbuwfY7j8hV6lI6iHsKnQU","domain":".google.com","path":"/","expires":1643893958.229864,"size":178,"httpOnly":true,"secure":true,"session":false,"sameSite":"None"},{"name":"CONSENT","value":"YES+yt.388297243.en+FX+616","domain":".google.fr","path":"/","expires":2146723199.311162,"size":33,"httpOnly":false,"secure":true,"session":false,"sameSite":"None"},{"name":"NID","value":"220=iOnReLl4iJI6WPciHHCUSiEpOyhhmy9BiDNqX1JjMpQ-GCI6Fwh6aaY15xNDZJqSO0JkmMg4P1zz7IQak_TG0xhEMz0RcPzY3peSvHofxWvqH_JeqQ5_JzKxq551quVD4TnHx1u1oOoCg901Dygq9gKc_EAxI0QzxHpnnoQpGm8","domain":".google.fr","path":"/","expires":1643893958.311296,"size":178,"httpOnly":true,"secure":true,"session":false,"sameSite":"None"},{"name":"GPS","value":"1","domain":".youtube.com","path":"/","expires":1628084560.198063,"size":4,"httpOnly":true,"secure":true,"session":false},{"name":"__Host-GAPS","value":"1:QOX3XjG-bFdYIV-FOpK0Mh9btdEU7g:DX7Z9yx80c2kip4o","domain":"accounts.google.com","path":"/","expires":1691154760.333985,"size":60,"httpOnly":true,"secure":true,"session":false},{"name":"IDE","value":"AHWqTUkRjGI2tga6r76PZ3vt2oLGyT9EHXU-97ipwRH3ITwkFsPURrFxcFn0XYcc","domain":".doubleclick.net","path":"/","expires":1661778761.248869,"size":67,"httpOnly":true,"secure":true,"session":false,"sameSite":"None"}]}